<?xml version="1.0" encoding="utf-8"?>
<arch:spatialUnit xmlns:arch="http://ochre.lib.uchicago.edu/schema/SpatialUnit/SpatialUnit.xsd" xmlns:oc="http://opencontext.org/schema/space_schema_v1.xsd" xmlns:dc="http://purl.org/dc/elements/1.1/" xmlns:gml="http://www.opengis.net/gml" UUID="7F862D43-F8A5-400C-04C2-F4456109EF5C" ownedBy="F905BD53-C843-4349-0A46-48FF32B5F1BE">
  <arch:name>
    <arch:string>Sumter</arch:string>
  </arch:name>
  <oc:item_class>
    <oc:name>Region</oc:name>
    <oc:iconURI>http://opencontext.org/database/ui_images/med_oc_icons/region_50x50.jpg</oc:iconURI>
  </oc:item_class>
  <arch:observations>
    <arch:observation obsNumber="1">
      <oc:obs_metadata>
        <oc:source>api.geonames.org</oc:source>
      </oc:obs_metadata>
      <arch:properties>
        <arch:property>
          <arch:variableID>B90CA9CC-B313-4525-8F26-0896AE7D3ED2</arch:variableID>
          <arch:valueID>4010853E-1397-4857-413B-CFFDB03B94D9</arch:valueID>
          <oc:propid href="http://opencontext.org/properties/FC518928-7DB5-481F-79A8-553E7E6BDB84">FC518928-7DB5-481F-79A8-553E7E6BDB84</oc:propid>
          <oc:var_label type="nominal">Gazetteer reference</oc:var_label>
          <oc:show_val>Sumter County (GeoNames:4092386)</oc:show_val>
          <oc:linkedData>
            <oc:relationLink localType="variable" localID="B90CA9CC-B313-4525-8F26-0896AE7D3ED2" href="http://purl.org/dc/terms/references">
              <oc:vocabulary href="http://concordia.atlantides.org/">Concordia</oc:vocabulary>
              <oc:label>References</oc:label>
              <oc:targetLink localType="property" localID="FC518928-7DB5-481F-79A8-553E7E6BDB84" localURI="http://opencontext.org/properties/FC518928-7DB5-481F-79A8-553E7E6BDB84" href="http://www.geonames.org/4092386">
                <oc:vocabulary href="http://www.geonames.org/">GeoNames</oc:vocabulary>
                <oc:label>Sumter County</oc:label>
              </oc:targetLink>
            </oc:relationLink>
          </oc:linkedData>
        </arch:property>
        <arch:property>
          <arch:variableID>87556028-677C-4C59-BA35-AE509BC825AD</arch:variableID>
          <arch:valueID>82E50233-C43C-4460-BEBF-961DEB5B0C40</arch:valueID>
          <oc:propid href="http://opencontext.org/properties/0A2B25FD-9EDB-4F71-4068-2806A3C641D9">0A2B25FD-9EDB-4F71-4068-2806A3C641D9</oc:propid>
          <oc:var_label type="alphanumeric">County name</oc:var_label>
          <oc:show_val>Sumter County</oc:show_val>
        </arch:property>
        <arch:property>
          <arch:variableID>388665AC-280B-4A64-1CE3-787E1D3E77D3</arch:variableID>
          <arch:integer>119</arch:integer>
          <oc:propid href="http://opencontext.org/properties/590C027D-9B6A-4F1D-FFDB-20C7C68DF16E">590C027D-9B6A-4F1D-FFDB-20C7C68DF16E</oc:propid>
          <oc:var_label type="integer">County FIPS</oc:var_label>
          <oc:show_val>119</oc:show_val>
        </arch:property>
        <arch:property>
          <arch:variableID>36FC4802-F991-47A7-BAF7-3F08ED3F372B</arch:variableID>
          <arch:integer>1119</arch:integer>
          <oc:propid href="http://opencontext.org/properties/1729F971-3BEE-4527-1C02-B6550D583230">1729F971-3BEE-4527-1C02-B6550D583230</oc:propid>
          <oc:var_label type="integer">FIPS</oc:var_label>
          <oc:show_val>01119</oc:show_val>
        </arch:property>
      </arch:properties>
    </arch:observation>
  </arch:observations>
  <oc:context>
    <oc:tree id="default">
      <oc:parent href="http://opencontext.org/subjects/2A1B75E6-8C79-49B9-873A-A2E006669691">
        <oc:name>United States</oc:name>
        <oc:id>2A1B75E6-8C79-49B9-873A-A2E006669691</oc:id>
        <oc:level>2</oc:level>
        <oc:item_class>
          <oc:name>Region</oc:name>
          <oc:iconURI>http://opencontext.org/database/ui_images/med_oc_icons/region_30x30.jpg</oc:iconURI>
        </oc:item_class>
      </oc:parent>
      <oc:parent href="http://opencontext.org/subjects/9D7BB146-63E1-47CF-AA85-D2061984381E">
        <oc:name>Alabama</oc:name>
        <oc:id>9D7BB146-63E1-47CF-AA85-D2061984381E</oc:id>
        <oc:level>1</oc:level>
        <oc:item_class>
          <oc:name>Region</oc:name>
          <oc:iconURI>http://opencontext.org/database/ui_images/med_oc_icons/region_30x30.jpg</oc:iconURI>
        </oc:item_class>
      </oc:parent>
    </oc:tree>
  </oc:context>
  <oc:children>
    <oc:tree id="default">
      <oc:child href="http://opencontext.org/subjects/EB650C60-E396-43FC-0AFA-9261329ABBCE">
        <oc:name>GR140</oc:name>
        <oc:id>EB650C60-E396-43FC-0AFA-9261329ABBCE</oc:id>
        <oc:item_class>
          <oc:name>Site</oc:name>
          <oc:iconURI>http://opencontext.org/database/ui_images/med_oc_icons/site_30x30.jpg</oc:iconURI>
        </oc:item_class>
      </oc:child>
      <oc:child href="http://opencontext.org/subjects/6A0656D0-34DD-4902-0C9D-D62F9D36D69D">
        <oc:name>GR28</oc:name>
        <oc:id>6A0656D0-34DD-4902-0C9D-D62F9D36D69D</oc:id>
        <oc:item_class>
          <oc:name>Site</oc:name>
          <oc:iconURI>http://opencontext.org/database/ui_images/med_oc_icons/site_30x30.jpg</oc:iconURI>
        </oc:item_class>
      </oc:child>
      <oc:child href="http://opencontext.org/subjects/DD02C319-E833-4501-FA14-5C6843D66DEB">
        <oc:name>GR30</oc:name>
        <oc:id>DD02C319-E833-4501-FA14-5C6843D66DEB</oc:id>
        <oc:item_class>
          <oc:name>Site</oc:name>
          <oc:iconURI>http://opencontext.org/database/ui_images/med_oc_icons/site_30x30.jpg</oc:iconURI>
        </oc:item_class>
      </oc:child>
      <oc:child href="http://opencontext.org/subjects/0CB2D0C1-A2EC-4314-90DA-9B1A6E76D79E">
        <oc:name>GR41</oc:name>
        <oc:id>0CB2D0C1-A2EC-4314-90DA-9B1A6E76D79E</oc:id>
        <oc:item_class>
          <oc:name>Site</oc:name>
          <oc:iconURI>http://opencontext.org/database/ui_images/med_oc_icons/site_30x30.jpg</oc:iconURI>
        </oc:item_class>
      </oc:child>
      <oc:child href="http://opencontext.org/subjects/23353D00-C9C9-429A-B33F-53064A78A83E">
        <oc:name>GR45</oc:name>
        <oc:id>23353D00-C9C9-429A-B33F-53064A78A83E</oc:id>
        <oc:item_class>
          <oc:name>Site</oc:name>
          <oc:iconURI>http://opencontext.org/database/ui_images/med_oc_icons/site_30x30.jpg</oc:iconURI>
        </oc:item_class>
      </oc:child>
      <oc:child href="http://opencontext.org/subjects/4C5C69E7-2368-4B86-B5A9-500EBD66C304">
        <oc:name>GR83</oc:name>
        <oc:id>4C5C69E7-2368-4B86-B5A9-500EBD66C304</oc:id>
        <oc:item_class>
          <oc:name>Site</oc:name>
          <oc:iconURI>http://opencontext.org/database/ui_images/med_oc_icons/site_30x30.jpg</oc:iconURI>
        </oc:item_class>
      </oc:child>
      <oc:child href="http://opencontext.org/subjects/E766F920-A1DB-4C30-18C3-257B46955A6B">
        <oc:name>GR84</oc:name>
        <oc:id>E766F920-A1DB-4C30-18C3-257B46955A6B</oc:id>
        <oc:item_class>
          <oc:name>Site</oc:name>
          <oc:iconURI>http://opencontext.org/database/ui_images/med_oc_icons/site_30x30.jpg</oc:iconURI>
        </oc:item_class>
      </oc:child>
      <oc:child href="http://opencontext.org/subjects/6C28E8F8-EE96-4BC5-D238-B7E12EB40EAA">
        <oc:name>LE470</oc:name>
        <oc:id>6C28E8F8-EE96-4BC5-D238-B7E12EB40EAA</oc:id>
        <oc:item_class>
          <oc:name>Site</oc:name>
          <oc:iconURI>http://opencontext.org/database/ui_images/med_oc_icons/site_30x30.jpg</oc:iconURI>
        </oc:item_class>
      </oc:child>
      <oc:child href="http://opencontext.org/subjects/3214620B-BED1-4D11-6B97-4653C6BC5DF7">
        <oc:name>SU1</oc:name>
        <oc:id>3214620B-BED1-4D11-6B97-4653C6BC5DF7</oc:id>
        <oc:item_class>
          <oc:name>Site</oc:name>
          <oc:iconURI>http://opencontext.org/database/ui_images/med_oc_icons/site_30x30.jpg</oc:iconURI>
        </oc:item_class>
      </oc:child>
      <oc:child href="http://opencontext.org/subjects/871F485D-8793-4427-C39E-BA1C3F82D5FB">
        <oc:name>SU100</oc:name>
        <oc:id>871F485D-8793-4427-C39E-BA1C3F82D5FB</oc:id>
        <oc:item_class>
          <oc:name>Site</oc:name>
          <oc:iconURI>http://opencontext.org/database/ui_images/med_oc_icons/site_30x30.jpg</oc:iconURI>
        </oc:item_class>
      </oc:child>
      <oc:child href="http://opencontext.org/subjects/A6F1C6B7-D060-46B8-E99D-2FA5D6F34BBF">
        <oc:name>SU102</oc:name>
        <oc:id>A6F1C6B7-D060-46B8-E99D-2FA5D6F34BBF</oc:id>
        <oc:item_class>
          <oc:name>Site</oc:name>
          <oc:iconURI>http://opencontext.org/database/ui_images/med_oc_icons/site_30x30.jpg</oc:iconURI>
        </oc:item_class>
      </oc:child>
      <oc:child href="http://opencontext.org/subjects/690F2292-C5DC-4966-5F32-61B3BE595FB4">
        <oc:name>SU103</oc:name>
        <oc:id>690F2292-C5DC-4966-5F32-61B3BE595FB4</oc:id>
        <oc:item_class>
          <oc:name>Site</oc:name>
          <oc:iconURI>http://opencontext.org/database/ui_images/med_oc_icons/site_30x30.jpg</oc:iconURI>
        </oc:item_class>
      </oc:child>
      <oc:child href="http://opencontext.org/subjects/5B524AD1-68F2-494B-ABCC-674FBF5ED753">
        <oc:name>SU104</oc:name>
        <oc:id>5B524AD1-68F2-494B-ABCC-674FBF5ED753</oc:id>
        <oc:item_class>
          <oc:name>Site</oc:name>
          <oc:iconURI>http://opencontext.org/database/ui_images/med_oc_icons/site_30x30.jpg</oc:iconURI>
        </oc:item_class>
      </oc:child>
      <oc:child href="http://opencontext.org/subjects/CFAF70AF-0D87-4B59-BDAE-F7A64A7E76F3">
        <oc:name>SU105</oc:name>
        <oc:id>CFAF70AF-0D87-4B59-BDAE-F7A64A7E76F3</oc:id>
        <oc:item_class>
          <oc:name>Site</oc:name>
          <oc:iconURI>http://opencontext.org/database/ui_images/med_oc_icons/site_30x30.jpg</oc:iconURI>
        </oc:item_class>
      </oc:child>
      <oc:child href="http://opencontext.org/subjects/09D16868-52AA-48DA-DFA1-97EE3E6B12B6">
        <oc:name>SU106</oc:name>
        <oc:id>09D16868-52AA-48DA-DFA1-97EE3E6B12B6</oc:id>
        <oc:item_class>
          <oc:name>Site</oc:name>
          <oc:iconURI>http://opencontext.org/database/ui_images/med_oc_icons/site_30x30.jpg</oc:iconURI>
        </oc:item_class>
      </oc:child>
      <oc:child href="http://opencontext.org/subjects/3D6D6E49-B4A8-4F0A-760D-8F6D1A79B553">
        <oc:name>SU107</oc:name>
        <oc:id>3D6D6E49-B4A8-4F0A-760D-8F6D1A79B553</oc:id>
        <oc:item_class>
          <oc:name>Site</oc:name>
          <oc:iconURI>http://opencontext.org/database/ui_images/med_oc_icons/site_30x30.jpg</oc:iconURI>
        </oc:item_class>
      </oc:child>
      <oc:child href="http://opencontext.org/subjects/9A9BABAD-52CF-4A22-3EFE-3CE3BCF6815F">
        <oc:name>SU108</oc:name>
        <oc:id>9A9BABAD-52CF-4A22-3EFE-3CE3BCF6815F</oc:id>
        <oc:item_class>
          <oc:name>Site</oc:name>
          <oc:iconURI>http://opencontext.org/database/ui_images/med_oc_icons/site_30x30.jpg</oc:iconURI>
        </oc:item_class>
      </oc:child>
      <oc:child href="http://opencontext.org/subjects/0BC617DD-C5C9-4A9B-0837-25AD83328D4C">
        <oc:name>SU109</oc:name>
        <oc:id>0BC617DD-C5C9-4A9B-0837-25AD83328D4C</oc:id>
        <oc:item_class>
          <oc:name>Site</oc:name>
          <oc:iconURI>http://opencontext.org/database/ui_images/med_oc_icons/site_30x30.jpg</oc:iconURI>
        </oc:item_class>
      </oc:child>
      <oc:child href="http://opencontext.org/subjects/8D95D203-B73E-45E7-3AF7-DE4960772886">
        <oc:name>SU110</oc:name>
        <oc:id>8D95D203-B73E-45E7-3AF7-DE4960772886</oc:id>
        <oc:item_class>
          <oc:name>Site</oc:name>
          <oc:iconURI>http://opencontext.org/database/ui_images/med_oc_icons/site_30x30.jpg</oc:iconURI>
        </oc:item_class>
      </oc:child>
      <oc:child href="http://opencontext.org/subjects/F885CDA3-ED43-4A14-7F32-7F7AE88A2610">
        <oc:name>SU111</oc:name>
        <oc:id>F885CDA3-ED43-4A14-7F32-7F7AE88A2610</oc:id>
        <oc:item_class>
          <oc:name>Site</oc:name>
          <oc:iconURI>http://opencontext.org/database/ui_images/med_oc_icons/site_30x30.jpg</oc:iconURI>
        </oc:item_class>
      </oc:child>
      <oc:child href="http://opencontext.org/subjects/0A483B3A-6A12-4BBC-101A-A0B96768F814">
        <oc:name>SU112</oc:name>
        <oc:id>0A483B3A-6A12-4BBC-101A-A0B96768F814</oc:id>
        <oc:item_class>
          <oc:name>Site</oc:name>
          <oc:iconURI>http://opencontext.org/database/ui_images/med_oc_icons/site_30x30.jpg</oc:iconURI>
        </oc:item_class>
      </oc:child>
      <oc:child href="http://opencontext.org/subjects/F5837664-74F5-4799-71DA-8CED3C85C9E4">
        <oc:name>SU113</oc:name>
        <oc:id>F5837664-74F5-4799-71DA-8CED3C85C9E4</oc:id>
        <oc:item_class>
          <oc:name>Site</oc:name>
          <oc:iconURI>http://opencontext.org/database/ui_images/med_oc_icons/site_30x30.jpg</oc:iconURI>
        </oc:item_class>
      </oc:child>
      <oc:child href="http://opencontext.org/subjects/4CE41B80-FBA2-40D0-81B8-E0FBF426BBE2">
        <oc:name>SU114</oc:name>
        <oc:id>4CE41B80-FBA2-40D0-81B8-E0FBF426BBE2</oc:id>
        <oc:item_class>
          <oc:name>Site</oc:name>
          <oc:iconURI>http://opencontext.org/database/ui_images/med_oc_icons/site_30x30.jpg</oc:iconURI>
        </oc:item_class>
      </oc:child>
      <oc:child href="http://opencontext.org/subjects/07BF7C05-D333-42D0-F51F-E9C0D9712904">
        <oc:name>SU115</oc:name>
        <oc:id>07BF7C05-D333-42D0-F51F-E9C0D9712904</oc:id>
        <oc:item_class>
          <oc:name>Site</oc:name>
          <oc:iconURI>http://opencontext.org/database/ui_images/med_oc_icons/site_30x30.jpg</oc:iconURI>
        </oc:item_class>
      </oc:child>
      <oc:child href="http://opencontext.org/subjects/317DF3B0-64CD-4E79-AC06-EC3DDC9F7B4B">
        <oc:name>SU116</oc:name>
        <oc:id>317DF3B0-64CD-4E79-AC06-EC3DDC9F7B4B</oc:id>
        <oc:item_class>
          <oc:name>Site</oc:name>
          <oc:iconURI>http://opencontext.org/database/ui_images/med_oc_icons/site_30x30.jpg</oc:iconURI>
        </oc:item_class>
      </oc:child>
      <oc:child href="http://opencontext.org/subjects/899BC418-FF90-40A0-69ED-4CCE46011A80">
        <oc:name>SU117</oc:name>
        <oc:id>899BC418-FF90-40A0-69ED-4CCE46011A80</oc:id>
        <oc:item_class>
          <oc:name>Site</oc:name>
          <oc:iconURI>http://opencontext.org/database/ui_images/med_oc_icons/site_30x30.jpg</oc:iconURI>
        </oc:item_class>
      </oc:child>
      <oc:child href="http://opencontext.org/subjects/2B7644EE-7B26-4117-718C-956E7DF66C2A">
        <oc:name>SU118</oc:name>
        <oc:id>2B7644EE-7B26-4117-718C-956E7DF66C2A</oc:id>
        <oc:item_class>
          <oc:name>Site</oc:name>
          <oc:iconURI>http://opencontext.org/database/ui_images/med_oc_icons/site_30x30.jpg</oc:iconURI>
        </oc:item_class>
      </oc:child>
      <oc:child href="http://opencontext.org/subjects/216C3F28-F020-41F6-CB0D-C057C390EBB7">
        <oc:name>SU119</oc:name>
        <oc:id>216C3F28-F020-41F6-CB0D-C057C390EBB7</oc:id>
        <oc:item_class>
          <oc:name>Site</oc:name>
          <oc:iconURI>http://opencontext.org/database/ui_images/med_oc_icons/site_30x30.jpg</oc:iconURI>
        </oc:item_class>
      </oc:child>
      <oc:child href="http://opencontext.org/subjects/0D062BB4-88DD-4AB5-4A04-AA2F33D9B95B">
        <oc:name>SU12</oc:name>
        <oc:id>0D062BB4-88DD-4AB5-4A04-AA2F33D9B95B</oc:id>
        <oc:item_class>
          <oc:name>Site</oc:name>
          <oc:iconURI>http://opencontext.org/database/ui_images/med_oc_icons/site_30x30.jpg</oc:iconURI>
        </oc:item_class>
      </oc:child>
      <oc:child href="http://opencontext.org/subjects/C4A49A97-F433-48AD-1CB4-41AB0020DAB5">
        <oc:name>SU120</oc:name>
        <oc:id>C4A49A97-F433-48AD-1CB4-41AB0020DAB5</oc:id>
        <oc:item_class>
          <oc:name>Site</oc:name>
          <oc:iconURI>http://opencontext.org/database/ui_images/med_oc_icons/site_30x30.jpg</oc:iconURI>
        </oc:item_class>
      </oc:child>
      <oc:child href="http://opencontext.org/subjects/E69D125A-42CA-48AE-7C83-F55F4868D342">
        <oc:name>SU121</oc:name>
        <oc:id>E69D125A-42CA-48AE-7C83-F55F4868D342</oc:id>
        <oc:item_class>
          <oc:name>Site</oc:name>
          <oc:iconURI>http://opencontext.org/database/ui_images/med_oc_icons/site_30x30.jpg</oc:iconURI>
        </oc:item_class>
      </oc:child>
      <oc:child href="http://opencontext.org/subjects/657A6084-7AFE-4F4F-731A-F95B07396A85">
        <oc:name>SU122</oc:name>
        <oc:id>657A6084-7AFE-4F4F-731A-F95B07396A85</oc:id>
        <oc:item_class>
          <oc:name>Site</oc:name>
          <oc:iconURI>http://opencontext.org/database/ui_images/med_oc_icons/site_30x30.jpg</oc:iconURI>
        </oc:item_class>
      </oc:child>
      <oc:child href="http://opencontext.org/subjects/22837AF9-6179-4661-8E20-C334B060DE83">
        <oc:name>SU123</oc:name>
        <oc:id>22837AF9-6179-4661-8E20-C334B060DE83</oc:id>
        <oc:item_class>
          <oc:name>Site</oc:name>
          <oc:iconURI>http://opencontext.org/database/ui_images/med_oc_icons/site_30x30.jpg</oc:iconURI>
        </oc:item_class>
      </oc:child>
      <oc:child href="http://opencontext.org/subjects/B9088C5D-A666-48BC-D560-58F7A709C3BE">
        <oc:name>SU124</oc:name>
        <oc:id>B9088C5D-A666-48BC-D560-58F7A709C3BE</oc:id>
        <oc:item_class>
          <oc:name>Site</oc:name>
          <oc:iconURI>http://opencontext.org/database/ui_images/med_oc_icons/site_30x30.jpg</oc:iconURI>
        </oc:item_class>
      </oc:child>
      <oc:child href="http://opencontext.org/subjects/16BD9C8A-7038-4034-5568-CD763CDB5582">
        <oc:name>SU126</oc:name>
        <oc:id>16BD9C8A-7038-4034-5568-CD763CDB5582</oc:id>
        <oc:item_class>
          <oc:name>Site</oc:name>
          <oc:iconURI>http://opencontext.org/database/ui_images/med_oc_icons/site_30x30.jpg</oc:iconURI>
        </oc:item_class>
      </oc:child>
      <oc:child href="http://opencontext.org/subjects/C01C1455-C25F-4397-12B3-E20DCDAC0C96">
        <oc:name>SU127</oc:name>
        <oc:id>C01C1455-C25F-4397-12B3-E20DCDAC0C96</oc:id>
        <oc:item_class>
          <oc:name>Site</oc:name>
          <oc:iconURI>http://opencontext.org/database/ui_images/med_oc_icons/site_30x30.jpg</oc:iconURI>
        </oc:item_class>
      </oc:child>
      <oc:child href="http://opencontext.org/subjects/96476ADF-2C72-44D8-4C9D-3E282E4C642D">
        <oc:name>SU129</oc:name>
        <oc:id>96476ADF-2C72-44D8-4C9D-3E282E4C642D</oc:id>
        <oc:item_class>
          <oc:name>Site</oc:name>
          <oc:iconURI>http://opencontext.org/database/ui_images/med_oc_icons/site_30x30.jpg</oc:iconURI>
        </oc:item_class>
      </oc:child>
      <oc:child href="http://opencontext.org/subjects/FB2CFFB8-82F6-4D92-6A93-53C55A8F0C13">
        <oc:name>SU13</oc:name>
        <oc:id>FB2CFFB8-82F6-4D92-6A93-53C55A8F0C13</oc:id>
        <oc:item_class>
          <oc:name>Site</oc:name>
          <oc:iconURI>http://opencontext.org/database/ui_images/med_oc_icons/site_30x30.jpg</oc:iconURI>
        </oc:item_class>
      </oc:child>
      <oc:child href="http://opencontext.org/subjects/6A7B7BA3-C6FD-4D64-A672-CC5B76ED233B">
        <oc:name>SU130</oc:name>
        <oc:id>6A7B7BA3-C6FD-4D64-A672-CC5B76ED233B</oc:id>
        <oc:item_class>
          <oc:name>Site</oc:name>
          <oc:iconURI>http://opencontext.org/database/ui_images/med_oc_icons/site_30x30.jpg</oc:iconURI>
        </oc:item_class>
      </oc:child>
      <oc:child href="http://opencontext.org/subjects/73748402-7786-474D-BF23-88FB44B82556">
        <oc:name>SU131</oc:name>
        <oc:id>73748402-7786-474D-BF23-88FB44B82556</oc:id>
        <oc:item_class>
          <oc:name>Site</oc:name>
          <oc:iconURI>http://opencontext.org/database/ui_images/med_oc_icons/site_30x30.jpg</oc:iconURI>
        </oc:item_class>
      </oc:child>
      <oc:child href="http://opencontext.org/subjects/D7977270-C8CE-4E6A-ACAB-0B0DC1CDFF9B">
        <oc:name>SU132</oc:name>
        <oc:id>D7977270-C8CE-4E6A-ACAB-0B0DC1CDFF9B</oc:id>
        <oc:item_class>
          <oc:name>Site</oc:name>
          <oc:iconURI>http://opencontext.org/database/ui_images/med_oc_icons/site_30x30.jpg</oc:iconURI>
        </oc:item_class>
      </oc:child>
      <oc:child href="http://opencontext.org/subjects/D85259C3-9BBD-4D51-F91D-A411A672570F">
        <oc:name>SU133</oc:name>
        <oc:id>D85259C3-9BBD-4D51-F91D-A411A672570F</oc:id>
        <oc:item_class>
          <oc:name>Site</oc:name>
          <oc:iconURI>http://opencontext.org/database/ui_images/med_oc_icons/site_30x30.jpg</oc:iconURI>
        </oc:item_class>
      </oc:child>
      <oc:child href="http://opencontext.org/subjects/050C1EE3-5C1C-4317-51E4-B5AAC54ED282">
        <oc:name>SU134</oc:name>
        <oc:id>050C1EE3-5C1C-4317-51E4-B5AAC54ED282</oc:id>
        <oc:item_class>
          <oc:name>Site</oc:name>
          <oc:iconURI>http://opencontext.org/database/ui_images/med_oc_icons/site_30x30.jpg</oc:iconURI>
        </oc:item_class>
      </oc:child>
      <oc:child href="http://opencontext.org/subjects/C5028A76-DB2E-412A-4D45-8FC82A02514C">
        <oc:name>SU135</oc:name>
        <oc:id>C5028A76-DB2E-412A-4D45-8FC82A02514C</oc:id>
        <oc:item_class>
          <oc:name>Site</oc:name>
          <oc:iconURI>http://opencontext.org/database/ui_images/med_oc_icons/site_30x30.jpg</oc:iconURI>
        </oc:item_class>
      </oc:child>
      <oc:child href="http://opencontext.org/subjects/031ACE5C-CD4D-4069-3823-3866A3F17111">
        <oc:name>SU136</oc:name>
        <oc:id>031ACE5C-CD4D-4069-3823-3866A3F17111</oc:id>
        <oc:item_class>
          <oc:name>Site</oc:name>
          <oc:iconURI>http://opencontext.org/database/ui_images/med_oc_icons/site_30x30.jpg</oc:iconURI>
        </oc:item_class>
      </oc:child>
      <oc:child href="http://opencontext.org/subjects/D666177B-B6F9-4C8E-2B78-D16144B09B51">
        <oc:name>SU137</oc:name>
        <oc:id>D666177B-B6F9-4C8E-2B78-D16144B09B51</oc:id>
        <oc:item_class>
          <oc:name>Site</oc:name>
          <oc:iconURI>http://opencontext.org/database/ui_images/med_oc_icons/site_30x30.jpg</oc:iconURI>
        </oc:item_class>
      </oc:child>
      <oc:child href="http://opencontext.org/subjects/B8EE8096-9984-4F0E-A39A-EE6A09B1A4E3">
        <oc:name>SU138</oc:name>
        <oc:id>B8EE8096-9984-4F0E-A39A-EE6A09B1A4E3</oc:id>
        <oc:item_class>
          <oc:name>Site</oc:name>
          <oc:iconURI>http://opencontext.org/database/ui_images/med_oc_icons/site_30x30.jpg</oc:iconURI>
        </oc:item_class>
      </oc:child>
      <oc:child href="http://opencontext.org/subjects/70063EEB-0F8A-427D-46F6-8F87C2B5244E">
        <oc:name>SU139</oc:name>
        <oc:id>70063EEB-0F8A-427D-46F6-8F87C2B5244E</oc:id>
        <oc:item_class>
          <oc:name>Site</oc:name>
          <oc:iconURI>http://opencontext.org/database/ui_images/med_oc_icons/site_30x30.jpg</oc:iconURI>
        </oc:item_class>
      </oc:child>
      <oc:child href="http://opencontext.org/subjects/3F4F1E84-543A-48FE-EEDB-A9A5BB317339">
        <oc:name>SU14</oc:name>
        <oc:id>3F4F1E84-543A-48FE-EEDB-A9A5BB317339</oc:id>
        <oc:item_class>
          <oc:name>Site</oc:name>
          <oc:iconURI>http://opencontext.org/database/ui_images/med_oc_icons/site_30x30.jpg</oc:iconURI>
        </oc:item_class>
      </oc:child>
      <oc:child href="http://opencontext.org/subjects/AC3A2CEF-651E-4DDC-2262-BF220B590031">
        <oc:name>SU140</oc:name>
        <oc:id>AC3A2CEF-651E-4DDC-2262-BF220B590031</oc:id>
        <oc:item_class>
          <oc:name>Site</oc:name>
          <oc:iconURI>http://opencontext.org/database/ui_images/med_oc_icons/site_30x30.jpg</oc:iconURI>
        </oc:item_class>
      </oc:child>
      <oc:child href="http://opencontext.org/subjects/5CB59BC1-3AB2-4E28-9329-5F324A05454E">
        <oc:name>SU141</oc:name>
        <oc:id>5CB59BC1-3AB2-4E28-9329-5F324A05454E</oc:id>
        <oc:item_class>
          <oc:name>Site</oc:name>
          <oc:iconURI>http://opencontext.org/database/ui_images/med_oc_icons/site_30x30.jpg</oc:iconURI>
        </oc:item_class>
      </oc:child>
      <oc:child href="http://opencontext.org/subjects/E5217107-223F-4F23-92C8-2F8340650E38">
        <oc:name>SU142</oc:name>
        <oc:id>E5217107-223F-4F23-92C8-2F8340650E38</oc:id>
        <oc:item_class>
          <oc:name>Site</oc:name>
          <oc:iconURI>http://opencontext.org/database/ui_images/med_oc_icons/site_30x30.jpg</oc:iconURI>
        </oc:item_class>
      </oc:child>
      <oc:child href="http://opencontext.org/subjects/906E567B-90F8-4848-F973-B6F056A38A4B">
        <oc:name>SU143</oc:name>
        <oc:id>906E567B-90F8-4848-F973-B6F056A38A4B</oc:id>
        <oc:item_class>
          <oc:name>Site</oc:name>
          <oc:iconURI>http://opencontext.org/database/ui_images/med_oc_icons/site_30x30.jpg</oc:iconURI>
        </oc:item_class>
      </oc:child>
      <oc:child href="http://opencontext.org/subjects/5B935AE7-42F8-40DE-5F14-12C5E293DF11">
        <oc:name>SU144</oc:name>
        <oc:id>5B935AE7-42F8-40DE-5F14-12C5E293DF11</oc:id>
        <oc:item_class>
          <oc:name>Site</oc:name>
          <oc:iconURI>http://opencontext.org/database/ui_images/med_oc_icons/site_30x30.jpg</oc:iconURI>
        </oc:item_class>
      </oc:child>
      <oc:child href="http://opencontext.org/subjects/F2C3AE35-1BFF-4E50-7594-1C3720302E16">
        <oc:name>SU145</oc:name>
        <oc:id>F2C3AE35-1BFF-4E50-7594-1C3720302E16</oc:id>
        <oc:item_class>
          <oc:name>Site</oc:name>
          <oc:iconURI>http://opencontext.org/database/ui_images/med_oc_icons/site_30x30.jpg</oc:iconURI>
        </oc:item_class>
      </oc:child>
      <oc:child href="http://opencontext.org/subjects/C7DB768E-E607-4B9B-C3A0-EBE02DFC69CC">
        <oc:name>SU15</oc:name>
        <oc:id>C7DB768E-E607-4B9B-C3A0-EBE02DFC69CC</oc:id>
        <oc:item_class>
          <oc:name>Site</oc:name>
          <oc:iconURI>http://opencontext.org/database/ui_images/med_oc_icons/site_30x30.jpg</oc:iconURI>
        </oc:item_class>
      </oc:child>
      <oc:child href="http://opencontext.org/subjects/1F5D664B-59A8-41F7-2D1D-0BE5C2CCE85F">
        <oc:name>SU17</oc:name>
        <oc:id>1F5D664B-59A8-41F7-2D1D-0BE5C2CCE85F</oc:id>
        <oc:item_class>
          <oc:name>Site</oc:name>
          <oc:iconURI>http://opencontext.org/database/ui_images/med_oc_icons/site_30x30.jpg</oc:iconURI>
        </oc:item_class>
      </oc:child>
      <oc:child href="http://opencontext.org/subjects/B1CEA109-2690-4558-6C62-CDDA5AB65E43">
        <oc:name>SU18</oc:name>
        <oc:id>B1CEA109-2690-4558-6C62-CDDA5AB65E43</oc:id>
        <oc:item_class>
          <oc:name>Site</oc:name>
          <oc:iconURI>http://opencontext.org/database/ui_images/med_oc_icons/site_30x30.jpg</oc:iconURI>
        </oc:item_class>
      </oc:child>
      <oc:child href="http://opencontext.org/subjects/9EDF0DE4-9401-4A6C-7CE1-AE7A4A48C72B">
        <oc:name>SU19</oc:name>
        <oc:id>9EDF0DE4-9401-4A6C-7CE1-AE7A4A48C72B</oc:id>
        <oc:item_class>
          <oc:name>Site</oc:name>
          <oc:iconURI>http://opencontext.org/database/ui_images/med_oc_icons/site_30x30.jpg</oc:iconURI>
        </oc:item_class>
      </oc:child>
      <oc:child href="http://opencontext.org/subjects/A4F88D7C-49BB-496D-2A3F-876A3486D844">
        <oc:name>SU2</oc:name>
        <oc:id>A4F88D7C-49BB-496D-2A3F-876A3486D844</oc:id>
        <oc:item_class>
          <oc:name>Site</oc:name>
          <oc:iconURI>http://opencontext.org/database/ui_images/med_oc_icons/site_30x30.jpg</oc:iconURI>
        </oc:item_class>
      </oc:child>
      <oc:child href="http://opencontext.org/subjects/FAC0933C-3061-4F4B-D003-CA5F72C93FCA">
        <oc:name>SU20</oc:name>
        <oc:id>FAC0933C-3061-4F4B-D003-CA5F72C93FCA</oc:id>
        <oc:item_class>
          <oc:name>Site</oc:name>
          <oc:iconURI>http://opencontext.org/database/ui_images/med_oc_icons/site_30x30.jpg</oc:iconURI>
        </oc:item_class>
      </oc:child>
      <oc:child href="http://opencontext.org/subjects/60F7F4FB-D632-4442-6463-7A6EB5DCBD32">
        <oc:name>SU21</oc:name>
        <oc:id>60F7F4FB-D632-4442-6463-7A6EB5DCBD32</oc:id>
        <oc:item_class>
          <oc:name>Site</oc:name>
          <oc:iconURI>http://opencontext.org/database/ui_images/med_oc_icons/site_30x30.jpg</oc:iconURI>
        </oc:item_class>
      </oc:child>
      <oc:child href="http://opencontext.org/subjects/159ED278-7CEB-455F-F017-B1F07444DEC5">
        <oc:name>SU22</oc:name>
        <oc:id>159ED278-7CEB-455F-F017-B1F07444DEC5</oc:id>
        <oc:item_class>
          <oc:name>Site</oc:name>
          <oc:iconURI>http://opencontext.org/database/ui_images/med_oc_icons/site_30x30.jpg</oc:iconURI>
        </oc:item_class>
      </oc:child>
      <oc:child href="http://opencontext.org/subjects/94416AFB-21D8-43F3-435A-98B2937287A7">
        <oc:name>SU23</oc:name>
        <oc:id>94416AFB-21D8-43F3-435A-98B2937287A7</oc:id>
        <oc:item_class>
          <oc:name>Site</oc:name>
          <oc:iconURI>http://opencontext.org/database/ui_images/med_oc_icons/site_30x30.jpg</oc:iconURI>
        </oc:item_class>
      </oc:child>
      <oc:child href="http://opencontext.org/subjects/DA080EF2-55F0-4887-55C8-DDCD76B958CB">
        <oc:name>SU24</oc:name>
        <oc:id>DA080EF2-55F0-4887-55C8-DDCD76B958CB</oc:id>
        <oc:item_class>
          <oc:name>Site</oc:name>
          <oc:iconURI>http://opencontext.org/database/ui_images/med_oc_icons/site_30x30.jpg</oc:iconURI>
        </oc:item_class>
      </oc:child>
      <oc:child href="http://opencontext.org/subjects/7CB57E55-170F-4F63-9E37-2FA972799D1A">
        <oc:name>SU25</oc:name>
        <oc:id>7CB57E55-170F-4F63-9E37-2FA972799D1A</oc:id>
        <oc:item_class>
          <oc:name>Site</oc:name>
          <oc:iconURI>http://opencontext.org/database/ui_images/med_oc_icons/site_30x30.jpg</oc:iconURI>
        </oc:item_class>
      </oc:child>
      <oc:child href="http://opencontext.org/subjects/CEF7F099-563D-4BA0-FB99-291ED58974C9">
        <oc:name>SU27</oc:name>
        <oc:id>CEF7F099-563D-4BA0-FB99-291ED58974C9</oc:id>
        <oc:item_class>
          <oc:name>Site</oc:name>
          <oc:iconURI>http://opencontext.org/database/ui_images/med_oc_icons/site_30x30.jpg</oc:iconURI>
        </oc:item_class>
      </oc:child>
      <oc:child href="http://opencontext.org/subjects/FEF8021F-D357-406E-7517-33E9338215D8">
        <oc:name>SU28</oc:name>
        <oc:id>FEF8021F-D357-406E-7517-33E9338215D8</oc:id>
        <oc:item_class>
          <oc:name>Site</oc:name>
          <oc:iconURI>http://opencontext.org/database/ui_images/med_oc_icons/site_30x30.jpg</oc:iconURI>
        </oc:item_class>
      </oc:child>
      <oc:child href="http://opencontext.org/subjects/8A028BE5-5AB2-4EAC-3F83-D927A763B3D6">
        <oc:name>SU29</oc:name>
        <oc:id>8A028BE5-5AB2-4EAC-3F83-D927A763B3D6</oc:id>
        <oc:item_class>
          <oc:name>Site</oc:name>
          <oc:iconURI>http://opencontext.org/database/ui_images/med_oc_icons/site_30x30.jpg</oc:iconURI>
        </oc:item_class>
      </oc:child>
      <oc:child href="http://opencontext.org/subjects/DD6EC56B-25DC-4009-3F84-402FF8D05820">
        <oc:name>SU3</oc:name>
        <oc:id>DD6EC56B-25DC-4009-3F84-402FF8D05820</oc:id>
        <oc:item_class>
          <oc:name>Site</oc:name>
          <oc:iconURI>http://opencontext.org/database/ui_images/med_oc_icons/site_30x30.jpg</oc:iconURI>
        </oc:item_class>
      </oc:child>
      <oc:child href="http://opencontext.org/subjects/D6C555D3-9C69-45E0-362F-270DED7543ED">
        <oc:name>SU30</oc:name>
        <oc:id>D6C555D3-9C69-45E0-362F-270DED7543ED</oc:id>
        <oc:item_class>
          <oc:name>Site</oc:name>
          <oc:iconURI>http://opencontext.org/database/ui_images/med_oc_icons/site_30x30.jpg</oc:iconURI>
        </oc:item_class>
      </oc:child>
      <oc:child href="http://opencontext.org/subjects/938E880B-AB91-4B73-1933-F266C98D4E9D">
        <oc:name>SU31</oc:name>
        <oc:id>938E880B-AB91-4B73-1933-F266C98D4E9D</oc:id>
        <oc:item_class>
          <oc:name>Site</oc:name>
          <oc:iconURI>http://opencontext.org/database/ui_images/med_oc_icons/site_30x30.jpg</oc:iconURI>
        </oc:item_class>
      </oc:child>
      <oc:child href="http://opencontext.org/subjects/403AC6ED-DAD1-44B2-75C2-FCC93E2E778B">
        <oc:name>SU32</oc:name>
        <oc:id>403AC6ED-DAD1-44B2-75C2-FCC93E2E778B</oc:id>
        <oc:item_class>
          <oc:name>Site</oc:name>
          <oc:iconURI>http://opencontext.org/database/ui_images/med_oc_icons/site_30x30.jpg</oc:iconURI>
        </oc:item_class>
      </oc:child>
      <oc:child href="http://opencontext.org/subjects/192531A0-F64D-4DD1-794F-27200D2F8D77">
        <oc:name>SU33</oc:name>
        <oc:id>192531A0-F64D-4DD1-794F-27200D2F8D77</oc:id>
        <oc:item_class>
          <oc:name>Site</oc:name>
          <oc:iconURI>http://opencontext.org/database/ui_images/med_oc_icons/site_30x30.jpg</oc:iconURI>
        </oc:item_class>
      </oc:child>
      <oc:child href="http://opencontext.org/subjects/0E31A8CD-9FA2-4646-5BBD-872BA0821CEB">
        <oc:name>SU34</oc:name>
        <oc:id>0E31A8CD-9FA2-4646-5BBD-872BA0821CEB</oc:id>
        <oc:item_class>
          <oc:name>Site</oc:name>
          <oc:iconURI>http://opencontext.org/database/ui_images/med_oc_icons/site_30x30.jpg</oc:iconURI>
        </oc:item_class>
      </oc:child>
      <oc:child href="http://opencontext.org/subjects/D6AD4DEE-8BF1-471B-5F0E-94087CA2FAE9">
        <oc:name>SU35</oc:name>
        <oc:id>D6AD4DEE-8BF1-471B-5F0E-94087CA2FAE9</oc:id>
        <oc:item_class>
          <oc:name>Site</oc:name>
          <oc:iconURI>http://opencontext.org/database/ui_images/med_oc_icons/site_30x30.jpg</oc:iconURI>
        </oc:item_class>
      </oc:child>
      <oc:child href="http://opencontext.org/subjects/D8697BF7-1B78-4011-57F9-29AE832A2EB9">
        <oc:name>SU36</oc:name>
        <oc:id>D8697BF7-1B78-4011-57F9-29AE832A2EB9</oc:id>
        <oc:item_class>
          <oc:name>Site</oc:name>
          <oc:iconURI>http://opencontext.org/database/ui_images/med_oc_icons/site_30x30.jpg</oc:iconURI>
        </oc:item_class>
      </oc:child>
      <oc:child href="http://opencontext.org/subjects/13385552-4FB3-4FF6-CF1D-0D694E557B5A">
        <oc:name>SU37</oc:name>
        <oc:id>13385552-4FB3-4FF6-CF1D-0D694E557B5A</oc:id>
        <oc:item_class>
          <oc:name>Site</oc:name>
          <oc:iconURI>http://opencontext.org/database/ui_images/med_oc_icons/site_30x30.jpg</oc:iconURI>
        </oc:item_class>
      </oc:child>
      <oc:child href="http://opencontext.org/subjects/D1350FA1-7F73-4176-9354-7740FECB07B8">
        <oc:name>SU38</oc:name>
        <oc:id>D1350FA1-7F73-4176-9354-7740FECB07B8</oc:id>
        <oc:item_class>
          <oc:name>Site</oc:name>
          <oc:iconURI>http://opencontext.org/database/ui_images/med_oc_icons/site_30x30.jpg</oc:iconURI>
        </oc:item_class>
      </oc:child>
      <oc:child href="http://opencontext.org/subjects/47E304A4-865B-4D2C-1403-9A4BCB7F8459">
        <oc:name>SU39</oc:name>
        <oc:id>47E304A4-865B-4D2C-1403-9A4BCB7F8459</oc:id>
        <oc:item_class>
          <oc:name>Site</oc:name>
          <oc:iconURI>http://opencontext.org/database/ui_images/med_oc_icons/site_30x30.jpg</oc:iconURI>
        </oc:item_class>
      </oc:child>
      <oc:child href="http://opencontext.org/subjects/B36BFBE0-9338-4DC3-FF21-2D51AACA57F4">
        <oc:name>SU4</oc:name>
        <oc:id>B36BFBE0-9338-4DC3-FF21-2D51AACA57F4</oc:id>
        <oc:item_class>
          <oc:name>Site</oc:name>
          <oc:iconURI>http://opencontext.org/database/ui_images/med_oc_icons/site_30x30.jpg</oc:iconURI>
        </oc:item_class>
      </oc:child>
      <oc:child href="http://opencontext.org/subjects/4D29BDA6-606D-4FC8-2BE2-5627E1FADCC1">
        <oc:name>SU40</oc:name>
        <oc:id>4D29BDA6-606D-4FC8-2BE2-5627E1FADCC1</oc:id>
        <oc:item_class>
          <oc:name>Site</oc:name>
          <oc:iconURI>http://opencontext.org/database/ui_images/med_oc_icons/site_30x30.jpg</oc:iconURI>
        </oc:item_class>
      </oc:child>
      <oc:child href="http://opencontext.org/subjects/9830E650-FB96-4BDC-732F-FE391C5889FB">
        <oc:name>SU41</oc:name>
        <oc:id>9830E650-FB96-4BDC-732F-FE391C5889FB</oc:id>
        <oc:item_class>
          <oc:name>Site</oc:name>
          <oc:iconURI>http://opencontext.org/database/ui_images/med_oc_icons/site_30x30.jpg</oc:iconURI>
        </oc:item_class>
      </oc:child>
      <oc:child href="http://opencontext.org/subjects/92AFA521-EDFD-4BA4-4811-EB7F4CBDF0C1">
        <oc:name>SU42</oc:name>
        <oc:id>92AFA521-EDFD-4BA4-4811-EB7F4CBDF0C1</oc:id>
        <oc:item_class>
          <oc:name>Site</oc:name>
          <oc:iconURI>http://opencontext.org/database/ui_images/med_oc_icons/site_30x30.jpg</oc:iconURI>
        </oc:item_class>
      </oc:child>
      <oc:child href="http://opencontext.org/subjects/EF39E2A7-129A-4C85-C946-D90394F3F754">
        <oc:name>SU43</oc:name>
        <oc:id>EF39E2A7-129A-4C85-C946-D90394F3F754</oc:id>
        <oc:item_class>
          <oc:name>Site</oc:name>
          <oc:iconURI>http://opencontext.org/database/ui_images/med_oc_icons/site_30x30.jpg</oc:iconURI>
        </oc:item_class>
      </oc:child>
      <oc:child href="http://opencontext.org/subjects/7C6620A3-A060-4001-7A1E-A6FE7332A420">
        <oc:name>SU44</oc:name>
        <oc:id>7C6620A3-A060-4001-7A1E-A6FE7332A420</oc:id>
        <oc:item_class>
          <oc:name>Site</oc:name>
          <oc:iconURI>http://opencontext.org/database/ui_images/med_oc_icons/site_30x30.jpg</oc:iconURI>
        </oc:item_class>
      </oc:child>
      <oc:child href="http://opencontext.org/subjects/DA654F2F-9DA1-4387-4972-A9B8AFB8D71D">
        <oc:name>SU45</oc:name>
        <oc:id>DA654F2F-9DA1-4387-4972-A9B8AFB8D71D</oc:id>
        <oc:item_class>
          <oc:name>Site</oc:name>
          <oc:iconURI>http://opencontext.org/database/ui_images/med_oc_icons/site_30x30.jpg</oc:iconURI>
        </oc:item_class>
      </oc:child>
      <oc:child href="http://opencontext.org/subjects/3B611977-0DDF-4B07-6EFB-8E4A39F4A483">
        <oc:name>SU46</oc:name>
        <oc:id>3B611977-0DDF-4B07-6EFB-8E4A39F4A483</oc:id>
        <oc:item_class>
          <oc:name>Site</oc:name>
          <oc:iconURI>http://opencontext.org/database/ui_images/med_oc_icons/site_30x30.jpg</oc:iconURI>
        </oc:item_class>
      </oc:child>
      <oc:child href="http://opencontext.org/subjects/8C4A1F29-1725-4BE4-D31D-FBEBD06CB6DB">
        <oc:name>SU47</oc:name>
        <oc:id>8C4A1F29-1725-4BE4-D31D-FBEBD06CB6DB</oc:id>
        <oc:item_class>
          <oc:name>Site</oc:name>
          <oc:iconURI>http://opencontext.org/database/ui_images/med_oc_icons/site_30x30.jpg</oc:iconURI>
        </oc:item_class>
      </oc:child>
      <oc:child href="http://opencontext.org/subjects/2E761040-2359-4E06-2549-4E2F3F42EEFC">
        <oc:name>SU48</oc:name>
        <oc:id>2E761040-2359-4E06-2549-4E2F3F42EEFC</oc:id>
        <oc:item_class>
          <oc:name>Site</oc:name>
          <oc:iconURI>http://opencontext.org/database/ui_images/med_oc_icons/site_30x30.jpg</oc:iconURI>
        </oc:item_class>
      </oc:child>
      <oc:child href="http://opencontext.org/subjects/5B20E712-8D3A-45D4-47C9-A040904FCCA9">
        <oc:name>SU49</oc:name>
        <oc:id>5B20E712-8D3A-45D4-47C9-A040904FCCA9</oc:id>
        <oc:item_class>
          <oc:name>Site</oc:name>
          <oc:iconURI>http://opencontext.org/database/ui_images/med_oc_icons/site_30x30.jpg</oc:iconURI>
        </oc:item_class>
      </oc:child>
      <oc:child href="http://opencontext.org/subjects/CFDAEA11-F97A-4FC5-0AD2-8CD70B7CFC8C">
        <oc:name>SU5</oc:name>
        <oc:id>CFDAEA11-F97A-4FC5-0AD2-8CD70B7CFC8C</oc:id>
        <oc:item_class>
          <oc:name>Site</oc:name>
          <oc:iconURI>http://opencontext.org/database/ui_images/med_oc_icons/site_30x30.jpg</oc:iconURI>
        </oc:item_class>
      </oc:child>
      <oc:child href="http://opencontext.org/subjects/909E1417-28AD-41EE-DCF9-FCF0F0297EFA">
        <oc:name>SU50</oc:name>
        <oc:id>909E1417-28AD-41EE-DCF9-FCF0F0297EFA</oc:id>
        <oc:item_class>
          <oc:name>Site</oc:name>
          <oc:iconURI>http://opencontext.org/database/ui_images/med_oc_icons/site_30x30.jpg</oc:iconURI>
        </oc:item_class>
      </oc:child>
      <oc:child href="http://opencontext.org/subjects/0A511082-709D-4E03-DA89-6586446CF146">
        <oc:name>SU51</oc:name>
        <oc:id>0A511082-709D-4E03-DA89-6586446CF146</oc:id>
        <oc:item_class>
          <oc:name>Site</oc:name>
          <oc:iconURI>http://opencontext.org/database/ui_images/med_oc_icons/site_30x30.jpg</oc:iconURI>
        </oc:item_class>
      </oc:child>
      <oc:child href="http://opencontext.org/subjects/B43E2DD3-EA60-467B-DF56-1E52C7056E15">
        <oc:name>SU52</oc:name>
        <oc:id>B43E2DD3-EA60-467B-DF56-1E52C7056E15</oc:id>
        <oc:item_class>
          <oc:name>Site</oc:name>
          <oc:iconURI>http://opencontext.org/database/ui_images/med_oc_icons/site_30x30.jpg</oc:iconURI>
        </oc:item_class>
      </oc:child>
      <oc:child href="http://opencontext.org/subjects/16875679-C988-4A27-A78F-90FC975BCB01">
        <oc:name>SU53</oc:name>
        <oc:id>16875679-C988-4A27-A78F-90FC975BCB01</oc:id>
        <oc:item_class>
          <oc:name>Site</oc:name>
          <oc:iconURI>http://opencontext.org/database/ui_images/med_oc_icons/site_30x30.jpg</oc:iconURI>
        </oc:item_class>
      </oc:child>
      <oc:child href="http://opencontext.org/subjects/2280D626-29CE-4543-CC83-FFAD228B21EE">
        <oc:name>SU54</oc:name>
        <oc:id>2280D626-29CE-4543-CC83-FFAD228B21EE</oc:id>
        <oc:item_class>
          <oc:name>Site</oc:name>
          <oc:iconURI>http://opencontext.org/database/ui_images/med_oc_icons/site_30x30.jpg</oc:iconURI>
        </oc:item_class>
      </oc:child>
      <oc:child href="http://opencontext.org/subjects/1C8DA15D-FB90-4180-8C2E-D6BBCDC2B934">
        <oc:name>SU55</oc:name>
        <oc:id>1C8DA15D-FB90-4180-8C2E-D6BBCDC2B934</oc:id>
        <oc:item_class>
          <oc:name>Site</oc:name>
          <oc:iconURI>http://opencontext.org/database/ui_images/med_oc_icons/site_30x30.jpg</oc:iconURI>
        </oc:item_class>
      </oc:child>
      <oc:child href="http://opencontext.org/subjects/47C6B454-103A-4BF8-302A-1ABF62B036D3">
        <oc:name>SU56</oc:name>
        <oc:id>47C6B454-103A-4BF8-302A-1ABF62B036D3</oc:id>
        <oc:item_class>
          <oc:name>Site</oc:name>
          <oc:iconURI>http://opencontext.org/database/ui_images/med_oc_icons/site_30x30.jpg</oc:iconURI>
        </oc:item_class>
      </oc:child>
      <oc:child href="http://opencontext.org/subjects/69C85C5E-2F1F-4B9F-9063-FBDE1786BFC5">
        <oc:name>SU57</oc:name>
        <oc:id>69C85C5E-2F1F-4B9F-9063-FBDE1786BFC5</oc:id>
        <oc:item_class>
          <oc:name>Site</oc:name>
          <oc:iconURI>http://opencontext.org/database/ui_images/med_oc_icons/site_30x30.jpg</oc:iconURI>
        </oc:item_class>
      </oc:child>
      <oc:child href="http://opencontext.org/subjects/64875EBF-9368-4905-F84A-97D1101A6618">
        <oc:name>SU58</oc:name>
        <oc:id>64875EBF-9368-4905-F84A-97D1101A6618</oc:id>
        <oc:item_class>
          <oc:name>Site</oc:name>
          <oc:iconURI>http://opencontext.org/database/ui_images/med_oc_icons/site_30x30.jpg</oc:iconURI>
        </oc:item_class>
      </oc:child>
      <oc:child href="http://opencontext.org/subjects/A3C3A552-EF4C-4B11-5660-DD83202DBC10">
        <oc:name>SU59</oc:name>
        <oc:id>A3C3A552-EF4C-4B11-5660-DD83202DBC10</oc:id>
        <oc:item_class>
          <oc:name>Site</oc:name>
          <oc:iconURI>http://opencontext.org/database/ui_images/med_oc_icons/site_30x30.jpg</oc:iconURI>
        </oc:item_class>
      </oc:child>
      <oc:child href="http://opencontext.org/subjects/47D1D953-3C04-4D01-E904-9143EA4D0C3A">
        <oc:name>SU6</oc:name>
        <oc:id>47D1D953-3C04-4D01-E904-9143EA4D0C3A</oc:id>
        <oc:item_class>
          <oc:name>Site</oc:name>
          <oc:iconURI>http://opencontext.org/database/ui_images/med_oc_icons/site_30x30.jpg</oc:iconURI>
        </oc:item_class>
      </oc:child>
      <oc:child href="http://opencontext.org/subjects/B1A78E74-5353-48C7-E4A3-571669E1F38E">
        <oc:name>SU60</oc:name>
        <oc:id>B1A78E74-5353-48C7-E4A3-571669E1F38E</oc:id>
        <oc:item_class>
          <oc:name>Site</oc:name>
          <oc:iconURI>http://opencontext.org/database/ui_images/med_oc_icons/site_30x30.jpg</oc:iconURI>
        </oc:item_class>
      </oc:child>
      <oc:child href="http://opencontext.org/subjects/AE25FC34-024A-4693-A835-FAF55B1AEF89">
        <oc:name>SU61</oc:name>
        <oc:id>AE25FC34-024A-4693-A835-FAF55B1AEF89</oc:id>
        <oc:item_class>
          <oc:name>Site</oc:name>
          <oc:iconURI>http://opencontext.org/database/ui_images/med_oc_icons/site_30x30.jpg</oc:iconURI>
        </oc:item_class>
      </oc:child>
      <oc:child href="http://opencontext.org/subjects/AF130978-8919-4C1D-4C2E-FBAC6B5CA82B">
        <oc:name>SU62</oc:name>
        <oc:id>AF130978-8919-4C1D-4C2E-FBAC6B5CA82B</oc:id>
        <oc:item_class>
          <oc:name>Site</oc:name>
          <oc:iconURI>http://opencontext.org/database/ui_images/med_oc_icons/site_30x30.jpg</oc:iconURI>
        </oc:item_class>
      </oc:child>
      <oc:child href="http://opencontext.org/subjects/6DDD09A6-858B-427B-4BC7-B7BB7F19AE6E">
        <oc:name>SU63</oc:name>
        <oc:id>6DDD09A6-858B-427B-4BC7-B7BB7F19AE6E</oc:id>
        <oc:item_class>
          <oc:name>Site</oc:name>
          <oc:iconURI>http://opencontext.org/database/ui_images/med_oc_icons/site_30x30.jpg</oc:iconURI>
        </oc:item_class>
      </oc:child>
      <oc:child href="http://opencontext.org/subjects/5DBF5A6A-6E52-42B9-76CF-EEA58EF0DE58">
        <oc:name>SU67</oc:name>
        <oc:id>5DBF5A6A-6E52-42B9-76CF-EEA58EF0DE58</oc:id>
        <oc:item_class>
          <oc:name>Site</oc:name>
          <oc:iconURI>http://opencontext.org/database/ui_images/med_oc_icons/site_30x30.jpg</oc:iconURI>
        </oc:item_class>
      </oc:child>
      <oc:child href="http://opencontext.org/subjects/6313FFB1-8034-4CA7-B799-0DC75F4D970F">
        <oc:name>SU68</oc:name>
        <oc:id>6313FFB1-8034-4CA7-B799-0DC75F4D970F</oc:id>
        <oc:item_class>
          <oc:name>Site</oc:name>
          <oc:iconURI>http://opencontext.org/database/ui_images/med_oc_icons/site_30x30.jpg</oc:iconURI>
        </oc:item_class>
      </oc:child>
      <oc:child href="http://opencontext.org/subjects/2F30E0BB-CE63-42FF-D870-9BCC6D3326EB">
        <oc:name>SU69</oc:name>
        <oc:id>2F30E0BB-CE63-42FF-D870-9BCC6D3326EB</oc:id>
        <oc:item_class>
          <oc:name>Site</oc:name>
          <oc:iconURI>http://opencontext.org/database/ui_images/med_oc_icons/site_30x30.jpg</oc:iconURI>
        </oc:item_class>
      </oc:child>
      <oc:child href="http://opencontext.org/subjects/E0D3560B-0C36-4575-9262-26D3D5C97A0F">
        <oc:name>SU70</oc:name>
        <oc:id>E0D3560B-0C36-4575-9262-26D3D5C97A0F</oc:id>
        <oc:item_class>
          <oc:name>Site</oc:name>
          <oc:iconURI>http://opencontext.org/database/ui_images/med_oc_icons/site_30x30.jpg</oc:iconURI>
        </oc:item_class>
      </oc:child>
      <oc:child href="http://opencontext.org/subjects/C3EACAC2-76B2-458F-BDE0-E5FCF84628D3">
        <oc:name>SU71</oc:name>
        <oc:id>C3EACAC2-76B2-458F-BDE0-E5FCF84628D3</oc:id>
        <oc:item_class>
          <oc:name>Site</oc:name>
          <oc:iconURI>http://opencontext.org/database/ui_images/med_oc_icons/site_30x30.jpg</oc:iconURI>
        </oc:item_class>
      </oc:child>
      <oc:child href="http://opencontext.org/subjects/A6F214DB-75FC-4397-BBD6-3606008E0C77">
        <oc:name>SU72</oc:name>
        <oc:id>A6F214DB-75FC-4397-BBD6-3606008E0C77</oc:id>
        <oc:item_class>
          <oc:name>Site</oc:name>
          <oc:iconURI>http://opencontext.org/database/ui_images/med_oc_icons/site_30x30.jpg</oc:iconURI>
        </oc:item_class>
      </oc:child>
      <oc:child href="http://opencontext.org/subjects/270F0D40-2226-4E53-FEB9-95EADE86E2B4">
        <oc:name>SU73</oc:name>
        <oc:id>270F0D40-2226-4E53-FEB9-95EADE86E2B4</oc:id>
        <oc:item_class>
          <oc:name>Site</oc:name>
          <oc:iconURI>http://opencontext.org/database/ui_images/med_oc_icons/site_30x30.jpg</oc:iconURI>
        </oc:item_class>
      </oc:child>
      <oc:child href="http://opencontext.org/subjects/89DC2870-9B51-48AC-4B2F-0C450DB948BD">
        <oc:name>SU74</oc:name>
        <oc:id>89DC2870-9B51-48AC-4B2F-0C450DB948BD</oc:id>
        <oc:item_class>
          <oc:name>Site</oc:name>
          <oc:iconURI>http://opencontext.org/database/ui_images/med_oc_icons/site_30x30.jpg</oc:iconURI>
        </oc:item_class>
      </oc:child>
      <oc:child href="http://opencontext.org/subjects/17057C9D-2B35-46C0-8C8D-F09714ABBC4A">
        <oc:name>SU75</oc:name>
        <oc:id>17057C9D-2B35-46C0-8C8D-F09714ABBC4A</oc:id>
        <oc:item_class>
          <oc:name>Site</oc:name>
          <oc:iconURI>http://opencontext.org/database/ui_images/med_oc_icons/site_30x30.jpg</oc:iconURI>
        </oc:item_class>
      </oc:child>
      <oc:child href="http://opencontext.org/subjects/9955CEE0-C2B3-42A6-8951-1374B6A5D468">
        <oc:name>SU76</oc:name>
        <oc:id>9955CEE0-C2B3-42A6-8951-1374B6A5D468</oc:id>
        <oc:item_class>
          <oc:name>Site</oc:name>
          <oc:iconURI>http://opencontext.org/database/ui_images/med_oc_icons/site_30x30.jpg</oc:iconURI>
        </oc:item_class>
      </oc:child>
      <oc:child href="http://opencontext.org/subjects/D9B46ED6-E95E-41E2-66FD-C65AFFE36EFD">
        <oc:name>SU77</oc:name>
        <oc:id>D9B46ED6-E95E-41E2-66FD-C65AFFE36EFD</oc:id>
        <oc:item_class>
          <oc:name>Site</oc:name>
          <oc:iconURI>http://opencontext.org/database/ui_images/med_oc_icons/site_30x30.jpg</oc:iconURI>
        </oc:item_class>
      </oc:child>
      <oc:child href="http://opencontext.org/subjects/53A11D72-6F72-4056-4330-0D156299C9E4">
        <oc:name>SU78</oc:name>
        <oc:id>53A11D72-6F72-4056-4330-0D156299C9E4</oc:id>
        <oc:item_class>
          <oc:name>Site</oc:name>
          <oc:iconURI>http://opencontext.org/database/ui_images/med_oc_icons/site_30x30.jpg</oc:iconURI>
        </oc:item_class>
      </oc:child>
      <oc:child href="http://opencontext.org/subjects/1E3DF5F7-8BDB-4AA5-583E-C4134673843F">
        <oc:name>SU79</oc:name>
        <oc:id>1E3DF5F7-8BDB-4AA5-583E-C4134673843F</oc:id>
        <oc:item_class>
          <oc:name>Site</oc:name>
          <oc:iconURI>http://opencontext.org/database/ui_images/med_oc_icons/site_30x30.jpg</oc:iconURI>
        </oc:item_class>
      </oc:child>
      <oc:child href="http://opencontext.org/subjects/71925271-5B6F-4F4F-95BE-4003DB8C6718">
        <oc:name>SU8</oc:name>
        <oc:id>71925271-5B6F-4F4F-95BE-4003DB8C6718</oc:id>
        <oc:item_class>
          <oc:name>Site</oc:name>
          <oc:iconURI>http://opencontext.org/database/ui_images/med_oc_icons/site_30x30.jpg</oc:iconURI>
        </oc:item_class>
      </oc:child>
      <oc:child href="http://opencontext.org/subjects/1D106E0E-DC17-46CB-0A30-3F5B41EB0CE9">
        <oc:name>SU80</oc:name>
        <oc:id>1D106E0E-DC17-46CB-0A30-3F5B41EB0CE9</oc:id>
        <oc:item_class>
          <oc:name>Site</oc:name>
          <oc:iconURI>http://opencontext.org/database/ui_images/med_oc_icons/site_30x30.jpg</oc:iconURI>
        </oc:item_class>
      </oc:child>
      <oc:child href="http://opencontext.org/subjects/4B4AF5CD-0CD3-40A8-3B3D-4197794A9338">
        <oc:name>SU81</oc:name>
        <oc:id>4B4AF5CD-0CD3-40A8-3B3D-4197794A9338</oc:id>
        <oc:item_class>
          <oc:name>Site</oc:name>
          <oc:iconURI>http://opencontext.org/database/ui_images/med_oc_icons/site_30x30.jpg</oc:iconURI>
        </oc:item_class>
      </oc:child>
      <oc:child href="http://opencontext.org/subjects/6BAF716B-88BB-44CB-F2EE-B33A97B32D5B">
        <oc:name>SU82</oc:name>
        <oc:id>6BAF716B-88BB-44CB-F2EE-B33A97B32D5B</oc:id>
        <oc:item_class>
          <oc:name>Site</oc:name>
          <oc:iconURI>http://opencontext.org/database/ui_images/med_oc_icons/site_30x30.jpg</oc:iconURI>
        </oc:item_class>
      </oc:child>
      <oc:child href="http://opencontext.org/subjects/10601984-EB17-4D09-613E-AE75C4C8A46C">
        <oc:name>SU83</oc:name>
        <oc:id>10601984-EB17-4D09-613E-AE75C4C8A46C</oc:id>
        <oc:item_class>
          <oc:name>Site</oc:name>
          <oc:iconURI>http://opencontext.org/database/ui_images/med_oc_icons/site_30x30.jpg</oc:iconURI>
        </oc:item_class>
      </oc:child>
      <oc:child href="http://opencontext.org/subjects/8B0D5CD2-AD57-440A-990C-79850E54B729">
        <oc:name>SU84</oc:name>
        <oc:id>8B0D5CD2-AD57-440A-990C-79850E54B729</oc:id>
        <oc:item_class>
          <oc:name>Site</oc:name>
          <oc:iconURI>http://opencontext.org/database/ui_images/med_oc_icons/site_30x30.jpg</oc:iconURI>
        </oc:item_class>
      </oc:child>
      <oc:child href="http://opencontext.org/subjects/E3C667FC-955C-4CBD-366C-8E674BB8C74A">
        <oc:name>SU85</oc:name>
        <oc:id>E3C667FC-955C-4CBD-366C-8E674BB8C74A</oc:id>
        <oc:item_class>
          <oc:name>Site</oc:name>
          <oc:iconURI>http://opencontext.org/database/ui_images/med_oc_icons/site_30x30.jpg</oc:iconURI>
        </oc:item_class>
      </oc:child>
      <oc:child href="http://opencontext.org/subjects/D0E14F3E-5ED2-4437-E511-5FCF29AB8CCF">
        <oc:name>SU86</oc:name>
        <oc:id>D0E14F3E-5ED2-4437-E511-5FCF29AB8CCF</oc:id>
        <oc:item_class>
          <oc:name>Site</oc:name>
          <oc:iconURI>http://opencontext.org/database/ui_images/med_oc_icons/site_30x30.jpg</oc:iconURI>
        </oc:item_class>
      </oc:child>
      <oc:child href="http://opencontext.org/subjects/6BB17215-630D-4001-A3AC-9A943449AFE6">
        <oc:name>SU87</oc:name>
        <oc:id>6BB17215-630D-4001-A3AC-9A943449AFE6</oc:id>
        <oc:item_class>
          <oc:name>Site</oc:name>
          <oc:iconURI>http://opencontext.org/database/ui_images/med_oc_icons/site_30x30.jpg</oc:iconURI>
        </oc:item_class>
      </oc:child>
      <oc:child href="http://opencontext.org/subjects/41FC59B8-DC01-4DBD-CD03-35F124A99F84">
        <oc:name>SU88</oc:name>
        <oc:id>41FC59B8-DC01-4DBD-CD03-35F124A99F84</oc:id>
        <oc:item_class>
          <oc:name>Site</oc:name>
          <oc:iconURI>http://opencontext.org/database/ui_images/med_oc_icons/site_30x30.jpg</oc:iconURI>
        </oc:item_class>
      </oc:child>
      <oc:child href="http://opencontext.org/subjects/E1F5DA53-A0EB-4FE9-C6C1-F2FB8AAC9D95">
        <oc:name>SU89</oc:name>
        <oc:id>E1F5DA53-A0EB-4FE9-C6C1-F2FB8AAC9D95</oc:id>
        <oc:item_class>
          <oc:name>Site</oc:name>
          <oc:iconURI>http://opencontext.org/database/ui_images/med_oc_icons/site_30x30.jpg</oc:iconURI>
        </oc:item_class>
      </oc:child>
      <oc:child href="http://opencontext.org/subjects/DB0E17CD-0DF3-47BE-FFDD-A94D9DBBA3FC">
        <oc:name>SU90</oc:name>
        <oc:id>DB0E17CD-0DF3-47BE-FFDD-A94D9DBBA3FC</oc:id>
        <oc:item_class>
          <oc:name>Site</oc:name>
          <oc:iconURI>http://opencontext.org/database/ui_images/med_oc_icons/site_30x30.jpg</oc:iconURI>
        </oc:item_class>
      </oc:child>
      <oc:child href="http://opencontext.org/subjects/6437B1F2-8AC4-461A-6BD6-62851CA05920">
        <oc:name>SU91</oc:name>
        <oc:id>6437B1F2-8AC4-461A-6BD6-62851CA05920</oc:id>
        <oc:item_class>
          <oc:name>Site</oc:name>
          <oc:iconURI>http://opencontext.org/database/ui_images/med_oc_icons/site_30x30.jpg</oc:iconURI>
        </oc:item_class>
      </oc:child>
      <oc:child href="http://opencontext.org/subjects/40F6123C-38A2-4714-4366-AE1307C31EB3">
        <oc:name>SU92</oc:name>
        <oc:id>40F6123C-38A2-4714-4366-AE1307C31EB3</oc:id>
        <oc:item_class>
          <oc:name>Site</oc:name>
          <oc:iconURI>http://opencontext.org/database/ui_images/med_oc_icons/site_30x30.jpg</oc:iconURI>
        </oc:item_class>
      </oc:child>
      <oc:child href="http://opencontext.org/subjects/15BD4578-F963-4588-70E6-A563468CDB34">
        <oc:name>SU93</oc:name>
        <oc:id>15BD4578-F963-4588-70E6-A563468CDB34</oc:id>
        <oc:item_class>
          <oc:name>Site</oc:name>
          <oc:iconURI>http://opencontext.org/database/ui_images/med_oc_icons/site_30x30.jpg</oc:iconURI>
        </oc:item_class>
      </oc:child>
    </oc:tree>
  </oc:children>
  <oc:metadata>
    <dc:title>Alabama Site Files: Sumter (Region)</dc:title>
    <dc:publisher>Open Context</dc:publisher>
    <dc:date>2014-07-30</dc:date>
    <dc:subject>Alabama</dc:subject>
    <dc:subject>archaeology</dc:subject>
    <dc:subject>cultural resource management</dc:subject>
    <dc:subject>DINAA</dc:subject>
    <dc:subject>North America</dc:subject>
    <dc:subject>site files</dc:subject>
    <dc:subject>state historical preservation office</dc:subject>
    <dc:creator href="http://opencontext.org/persons/1CD159BD-8A47-41CB-C68B-F29CD3110609">Office of Archaeological Research (OAR), University of Alabama</dc:creator>
    <dc:identifier>http://opencontext.org/subjects/7F862D43-F8A5-400C-04C2-F4456109EF5C</dc:identifier>
    <oc:project_name href="http://opencontext.org/projects/F905BD53-C843-4349-0A46-48FF32B5F1BE">Alabama Site Files</oc:project_name>
    <oc:pub_date>2014-07-30T00:00:00-07:00</oc:pub_date>
    <oc:coins>ctx_ver=Z39.88-2004&amp;rft_val_fmt=info%3Aofi%2Ffmt%3Akev%3Amtx%3Adc&amp;rft_val_fmt=info%3Aofi%2Ffmt%3Akev%3Amtx%3Adc&amp;rft.type=dataset&amp;rft.title=Alabama+Site+Files%3A+Sumter+%28Region%29&amp;rft.publisher=Open+Context&amp;rft.source=Open+Context&amp;rft.subject=Alabama&amp;rft.subject=archaeology&amp;rft.subject=cultural+resource+management&amp;rft.subject=DINAA&amp;rft.subject=North+America&amp;rft.subject=site+files&amp;rft.subject=state+historical+preservation+office&amp;rft.creator=Office+of+Archaeological+Research+%28OAR%29%2C+University+of+Alabama&amp;rft.identifier=http%3A%2F%2Fopencontext.org%2Fsubjects%2F7F862D43-F8A5-400C-04C2-F4456109EF5C</oc:coins>
    <oc:geo_reference>
      <oc:geo_lat>32.651826858521</oc:geo_lat>
      <oc:geo_long>-88.130165100098</oc:geo_long>
      <oc:metasource ref_type="self" href="http://opencontext.org/subjects/7F862D43-F8A5-400C-04C2-F4456109EF5C" specificity="-1">
        <oc:note>Data from geonames.org</oc:note>
        <oc:source_name>Sumter</oc:source_name>
        <oc:source_id>7F862D43-F8A5-400C-04C2-F4456109EF5C</oc:source_id>
      </oc:metasource>
    </oc:geo_reference>
    <oc:copyright_lic href="http://creativecommons.org/publicdomain/zero/1.0/">
      <oc:lic_name>Zero (Public Domain)</oc:lic_name>
      <oc:lic_vers>1</oc:lic_vers>
      <oc:lic_URI>http://creativecommons.org/publicdomain/zero/1.0/</oc:lic_URI>
      <oc:lic_icon_URI>http://i.creativecommons.org/p/zero/1.0/88x31.png</oc:lic_icon_URI>
    </oc:copyright_lic>
  </oc:metadata>
  <oc:social_usage>
    <oc:last_updated>2014-07-31T03:49:17-07:00</oc:last_updated>
    <oc:item_views>
      <oc:count>1</oc:count>
      <oc:view_time>2014/07/31 03:49:17</oc:view_time>
    </oc:item_views>
    <oc:user_tags/>
  </oc:social_usage>
</arch:spatialUnit>
